{"Type":"BATCHJOBGRPS","Key":"BFUABATCHJOB","MetaData":{"Folder":"","Id":"BFUABATCHJOB","Name":"BF-UA Batch Job Group for testing BF (weekly)"},"ConfigurationDependencies":{"REFFILENAMES":["BF-UA BJL"],"BATCHJOBS":["BF-UA 1551","BF-UA 1574","BF-UA 1640","BF-UA 1595","BF-UA 1707","BF-UA 2028","BF-UA 1522","BF-UA 1343","BF-UA 1484","BF-UA 1504","BF-UA 1505","BF-UA 1556"]},"ImportPolicies":{"RbaPermissions":{"All":"Skip","General":"Skip","User":"Skip"}},"AdditionalFiles":{},"Attributes":{"pBJOBGRP":"BFUABATCHJOB","pBJOBGRPNAME":"BF-UA Batch Job Group for testing BF (weekly)","pREFFILEIK-pREFFILE":"BF-UA BJL","pCALIK-pCAL":"","pFREECOM":"","pSENDSTART":false,"pSENDEND":false,"pSENDSTARTTO-pMAILGRP":"","pSENDENDTO-pMAILGRP":"","pSENDSUBSTART":false,"pSENDSUBFAIL":false,"pSENDSUBSTARTTO-pMAILGRP":"","pSENDSUBFAILTO-pMAILGRP":"","pSENDATTLOG":false,"pPMGIK-pPMG":"","pBJOBGRPCHGPARM":false,"pDONTREMOVETEMP":false,"pSENDSUBENDTO-pMAILGRP":"","pSENDSUBEND":false,"pIFCPKGORG":null,"pBJOBGRPFC1IK-pBJOBGRPFC1":"","pBJOBGRPFC2IK-pBJOBGRPFC2":"","pBJOBGRPFC3IK-pBJOBGRPFC3":"","pBJOBGRPFC4IK-pBJOBGRPFC4":"","pBJOBGRPFC5IK-pBJOBGRPFC5":"","tBATCHJOBGRPSSUB":[{"pSORT":1,"pBJOBIK-pBJOB":"BF-UA 1551","pBJOBFREQ":[12,"Every working day"],"pBJOBSTOP":false,"pBJOBACTIVE":true,"pBJOBONOK":null,"pBJOBONERROR":null},{"pSORT":2,"pBJOBIK-pBJOB":"BF-UA 1574","pBJOBFREQ":[12,"Every working day"],"pBJOBSTOP":false,"pBJOBACTIVE":true,"pBJOBONOK":null,"pBJOBONERROR":null},{"pSORT":3,"pBJOBIK-pBJOB":"BF-UA 1640","pBJOBFREQ":[12,"Every working day"],"pBJOBSTOP":false,"pBJOBACTIVE":true,"pBJOBONOK":null,"pBJOBONERROR":null},{"pSORT":4,"pBJOBIK-pBJOB":"BF-UA 1595","pBJOBFREQ":[12,"Every working day"],"pBJOBSTOP":false,"pBJOBACTIVE":true,"pBJOBONOK":null,"pBJOBONERROR":null},{"pSORT":5,"pBJOBIK-pBJOB":"BF-UA 1707","pBJOBFREQ":[12,"Every working day"],"pBJOBSTOP":false,"pBJOBACTIVE":true,"pBJOBONOK":null,"pBJOBONERROR":null},{"pSORT":6,"pBJOBIK-pBJOB":"BF-UA 2028","pBJOBFREQ":[12,"Every working day"],"pBJOBSTOP":false,"pBJOBACTIVE":true,"pBJOBONOK":null,"pBJOBONERROR":null},{"pSORT":7,"pBJOBIK-pBJOB":"BF-UA 1522","pBJOBFREQ":[12,"Every working day"],"pBJOBSTOP":true,"pBJOBACTIVE":true,"pBJOBONOK":null,"pBJOBONERROR":null},{"pSORT":8,"pBJOBIK-pBJOB":"BF-UA 1343","pBJOBFREQ":[12,"Every working day"],"pBJOBSTOP":true,"pBJOBACTIVE":true,"pBJOBONOK":null,"pBJOBONERROR":null},{"pSORT":9,"pBJOBIK-pBJOB":"BF-UA 1484","pBJOBFREQ":[12,"Every working day"],"pBJOBSTOP":false,"pBJOBACTIVE":true,"pBJOBONOK":null,"pBJOBONERROR":null},{"pSORT":10,"pBJOBIK-pBJOB":"BF-UA 1504","pBJOBFREQ":[12,"Every working day"],"pBJOBSTOP":false,"pBJOBACTIVE":true,"pBJOBONOK":null,"pBJOBONERROR":null},{"pSORT":11,"pBJOBIK-pBJOB":"BF-UA 1505","pBJOBFREQ":[12,"Every working day"],"pBJOBSTOP":false,"pBJOBACTIVE":true,"pBJOBONOK":null,"pBJOBONERROR":null},{"pSORT":12,"pBJOBIK-pBJOB":"BF-UA 1556","pBJOBFREQ":[12,"Every working day"],"pBJOBSTOP":false,"pBJOBACTIVE":true,"pBJOBONOK":null,"pBJOBONERROR":null}]}}